config/__init__.py
config/asgi.py
config/settings.py
config/urls.py
config/wsgi.py
django_realtime_logs/__init__.py
django_realtime_logs/apps.py
django_realtime_logs/consumers.py
django_realtime_logs/routing.py
django_realtime_logs/urls.py
django_realtime_logs/views.py
django_realtime_logs/templates/django_realtime_logs/logs.html
django_realtime_logs-0.1.2.dist-info/licenses/LICENSE
django_realtime_logs-0.1.2.dist-info/METADATA
django_realtime_logs-0.1.2.dist-info/WHEEL
django_realtime_logs-0.1.2.dist-info/top_level.txt
django_realtime_logs-0.1.2.dist-info/RECORD
