Metadata-Version: 2.4
Name: django-realtime-logs
Version: 0.1.2
Summary: Realtime log viewer for Django using Channels
Author: Pranav Dixit
Author-email: pranavdixit20@gmail.com
Classifier: Framework :: Django
Classifier: Programming Language :: Python :: 3
Classifier: License :: OSI Approved :: MIT License
Classifier: Operating System :: OS Independent
License-File: LICENSE
Requires-Dist: Django>=3.2
Requires-Dist: channels>=3.0
Dynamic: author
Dynamic: author-email
Dynamic: classifier
Dynamic: description
Dynamic: description-content-type
Dynamic: license-file
Dynamic: requires-dist
Dynamic: summary
